{
    "discordias": {
        "winners": [
            " Drothdarr" ,
            " MIKE SILVA",
            " JFSL",
            " Coxo",
            " Jondesu",
            " Rui Murteira Gomes",
            " 2 Coxos e Meio",
            " Mafia Alentejana",
            " JFSL",
            " JFSL",
            " EdgelordZuko",
            " JFSL",
            " Lomb",
            " BadCat",
            " L锚 no Alentege",
            " The Cult of UHU",
            " Rui Murteira Gomes"
        ],

        "tournaments": [
            "Disc贸rdia Lusitana #1 叼" ,
            "Disc贸rdia Lusitana #2 叼",
            "Disc贸rdia Lusitana #3 叼",
            "Disc贸rdia Lusitana #4 叼",
            "Disc贸rdia Lusitana #5 叼",
            "Disc贸rdia Lusitana #6 叼",
            "Disc贸rdia Lusitana #7 叼",
            "Disc贸rdia Lusitana #8 叼",
            "Disc贸rdia Lusitana #9 叼",
            "Disc贸rdia Lusitana #10 叼",
            "Disc贸rdia Lusitana #11 叼",
            "Disc贸rdia Lusitana #12 叼",
            "Disc贸rdia Lusitana #13 叼",
            "Disc贸rdia Lusitana #14 叼",
            "Disc贸rdia Lusitana #15 叼",
            "Disc贸rdia Ib茅rica Maio 21 叼桂",
            "Disc贸rdia Ib茅rica June 21 叼桂"
        ]
    },

    "onlines": {
       "winners":[
            " Jondesu",
            " Coxo",
            " Jondesu",
            " SC_Yin",
            " Jondesu",
            " JFSL",
            " ChiefJ"
    ],
        "tournaments": [
            "Deathphist League #1 PS4 叼",
            "Deathphist League #1 PC 叼",
            "Easter Wind Tuga Fist 2018 PC 叼",
            "Easter Wind Tuga Fist 2018 PS4 叼",
            "Comunidade Gamer Portuguesa Tekken 7 叼",
            "Deathphist League #2 PC 叼",
            "Deathphist League #2 PS4 叼"
            ]
        },
    
    "offlines": {
        "winners": [
            " Jondesu",
            " Cris",
            " Jondesu",
            " Jondesu",
            " Jondesu",
            " Seifer",
            " Coxo",
            " JFSL",
            " Cris",
            " Coxo",
            " Coxo",
            " Coxo",
            " Jondesu",
            " Cris",
            " Jondesu",
            " Coxo",
            " MIKE SILVA",
            " Jondesu",
            " MIKE SILVA",
            " Seifer",
            " MIKE SILVA"
        ],

    "tournaments":[
            "Lutinhas em Lisboa #5 叼",
            "tab#11 叼",
            "Road to Lockdown 叼",
            "Lockdown 2017 叼",
            "Last Chance Qualifier 叼",
            "Lutinhas em Lisboa #6 叼",
            "Super Combo #2 叼",
            "Lutinhas em Lisboa #7 叼",
            "Lockdown 2018 叼",
            "Braga Fight Fest #1 叼",
            "Super Combo #3 叼",
            "Finais Liga PTFighters 2018 叼",
            "Hold The L #1 叼",
            "Stone Fist #1 叼",
            "Lutinhas em Lisboa #8 叼",
            "Super Combo #4 叼",
            "Lutinhas em Lisboa #9 叼",
            "Stone Fist #2 叼",
            "IeSF World Championship Qualifier 2019 叼",
            "Finais Liga PTFighters 2019 叼",
            "Northern Cross #1 叼"
    ]

    }
}

